odoo9_addon_hr_timesheet_sheet_week_start_day-9.0.1.0.0-py2.7-nspkg.pth
odoo9_addon_hr_timesheet_sheet_week_start_day-9.0.1.0.0.dist-info/top_level.txt
odoo9_addon_hr_timesheet_sheet_week_start_day-9.0.1.0.0.dist-info/WHEEL
odoo9_addon_hr_timesheet_sheet_week_start_day-9.0.1.0.0.dist-info/RECORD
odoo9_addon_hr_timesheet_sheet_week_start_day-9.0.1.0.0.dist-info/metadata.json
odoo9_addon_hr_timesheet_sheet_week_start_day-9.0.1.0.0.dist-info/DESCRIPTION.rst
odoo9_addon_hr_timesheet_sheet_week_start_day-9.0.1.0.0.dist-info/METADATA
odoo9_addon_hr_timesheet_sheet_week_start_day-9.0.1.0.0.dist-info/namespace_packages.txt
odoo_addons/hr_timesheet_sheet_week_start_day/__openerp__.py
odoo_addons/hr_timesheet_sheet_week_start_day/__init__.py
odoo_addons/hr_timesheet_sheet_week_start_day/README.rst
odoo_addons/hr_timesheet_sheet_week_start_day/models/hr_timesheet_sheet.py
odoo_addons/hr_timesheet_sheet_week_start_day/models/__init__.py
odoo_addons/hr_timesheet_sheet_week_start_day/models/res_company.py
odoo_addons/hr_timesheet_sheet_week_start_day/views/res_company_view.xml
odoo_addons/hr_timesheet_sheet_week_start_day/tests/test_hr_timesheet_sheet_week_start_day.py
odoo_addons/hr_timesheet_sheet_week_start_day/tests/__init__.py
odoo_addons/hr_timesheet_sheet_week_start_day/static/description/icon.png
