Metadata-Version: 2.0
Name: odoo9-addon-hr-timesheet-sheet-week-start-day
Version: 9.0.1.0.0
Summary: Allows to define the week start date for Timesheets at company level
Home-page: http://www.eficent.com
Author: UNKNOWN
Author-email: UNKNOWN
License: AGPL-3
Platform: UNKNOWN
Requires-Dist: odoo (<9.1a,>=9.0a)
Classifier: Programming Language :: Python :: 2.7
Classifier: Framework :: Odoo
Classifier: License :: OSI Approved :: GNU Affero General Public License v3
